README.md
setup.cfg
setup.py
pypylon_opencv_viewer/__init__.py
pypylon_opencv_viewer/viewer.py
pypylon_opencv_viewer.egg-info/PKG-INFO
pypylon_opencv_viewer.egg-info/SOURCES.txt
pypylon_opencv_viewer.egg-info/dependency_links.txt
pypylon_opencv_viewer.egg-info/requires.txt
pypylon_opencv_viewer.egg-info/top_level.txt