Metadata-Version: 2.1
Name: pypylon-opencv-viewer
Version: 1.0.3
Summary: Impro function application while saving and getting image
Home-page: https://github.com/mbalatsko/pypylon-opencv-viewer
Author: Maksym Balatsko
Author-email: mbalatsko@gmail.com
License: MIT License
Download-URL: https://github.com/mbalatsko/pypylon-opencv-viewer/archive/1.0.3.tar.gz
Keywords: basler,pypylon,opencv,jypyter,pypylon viewer,opencv pypylon
Platform: UNKNOWN
Classifier: Programming Language :: Python :: 3
Classifier: Programming Language :: Python :: 3.0
Classifier: Programming Language :: Python :: 3.1
Classifier: Programming Language :: Python :: 3.2
Classifier: Programming Language :: Python :: 3.3
Classifier: Programming Language :: Python :: 3.4
Classifier: Programming Language :: Python :: 3.5
Classifier: Programming Language :: Python :: 3.6
Classifier: Programming Language :: Python :: 3.7
Classifier: Operating System :: OS Independent
